Metadata-Version: 2.4
Name: smoothglue_file_uploader
Version: 1.0.8
Summary: SmoothGlue GuC2 File Uploader: a Django app providing secure, pluggable uploads to S3, MinIO, or local storage with validation, checksums, and post-processing. Built for regulated and edge environments from the ground up.
Author: SmoothGlue
Project-URL: Homepage, https://braingu.com/solutions/smoothglue/
Requires-Python: >= 3.12
License-File: LICENSE
License-File: NOTICE
Requires-Dist: django>=4.2
Requires-Dist: minio>=7.2.16
Requires-Dist: boto3>=1.34.92
Requires-Dist: PyJWT>=2.10.1
Requires-Dist: markdown>=3.5.2
Requires-Dist: drf-spectacular>=0.26.5
Requires-Dist: drf-spectacular-sidecar>=2025.3.1
Dynamic: license-file
Dynamic: requires-python
